flastapi/__init__.py
flastapi/routing.py
flastapi/signature/__init__.py
flastapi/signature/exceptions.py
flastapi/signature/mapper.py
flastapi-0.1.0.dist-info/AUTHORS
flastapi-0.1.0.dist-info/LICENSE
flastapi-0.1.0.dist-info/METADATA
flastapi-0.1.0.dist-info/WHEEL
flastapi-0.1.0.dist-info/pbr.json
flastapi-0.1.0.dist-info/top_level.txt
flastapi-0.1.0.dist-info/RECORD
