Metadata-Version: 2.1
Name: flastapi
Version: 0.1.0
Summary: FastAPI-like interface plugin for Flask
Home-page: https://github.com/maarten-dp/flastapi
Author: Maarten De Paepe
Author-email: "maarten.de.paepe@gmail.com"
Classifier: Development Status :: 4 - Beta
Classifier: Operating System :: MacOS :: MacOS X
Classifier: Operating System :: Microsoft :: Windows
Classifier: Operating System :: POSIX
Classifier: License :: OSI Approved :: MIT License
Classifier: Programming Language :: Python
Classifier: Programming Language :: Python :: 3.7
Classifier: Programming Language :: Python :: 3.8
Classifier: Programming Language :: Python :: 3.9
Classifier: Programming Language :: Python :: 3.10
License-File: LICENSE
License-File: AUTHORS
